srcheck/__init__.py
srcheck/dataclass.py
srcheck/datasets.py
srcheck/main.py
srcheck/utils.py
srcheck/metrics/__init__.py
srcheck/metrics/lpips.py
srcheck/metrics/main.py
srcheck/metrics/ndvicheck.py
srcheck/metrics/pnsr.py
srcheck/metrics/psnr.py
srcheck/metrics/shanshan.py
srcheck/metrics/ssim.py
srcheck-0.1.6.dist-info/LICENSE
srcheck-0.1.6.dist-info/METADATA
srcheck-0.1.6.dist-info/WHEEL
srcheck-0.1.6.dist-info/top_level.txt
srcheck-0.1.6.dist-info/RECORD
