Metadata-Version: 2.1
Name: srcheck
Version: 0.1.6
Summary: An Agnostic Benchmark for Optical Remote Sensing Image Super-Resolution
Home-page: https://github.com/csaybar/srcheck
Author: Cesar Aybar Camacho
Author-email: csaybar@gmail.com
License: MIT
Classifier: Development Status :: 2 - Pre-Alpha
Classifier: License :: OSI Approved :: MIT License
Classifier: Programming Language :: Python
Classifier: Programming Language :: Python :: 3.6
Classifier: Programming Language :: Python :: 3.7
Classifier: Programming Language :: Python :: 3.8
Classifier: Programming Language :: Python :: 3.9
License-File: LICENSE
Requires-Dist: numpy
Requires-Dist: pydantic
Requires-Dist: alive-progress
Requires-Dist: orjson
Requires-Dist: timm
Requires-Dist: torchvision
